{"stat.useItem.minecraft.bow":1,"stat.useItem.minecraft.golden_apple":1,"stat.flyOneCm":93397,"stat.killEntity.Skeleton":4,"stat.walkOneCm":53389,"stat.jump":280,"stat.swimOneCm":625,"stat.playOneMinute":14682,"stat.fallOneCm":269,"achievement.openInventory":1,"stat.killEntity.Chicken":2,"stat.leaveGame":1,"stat.killEntity.Spider":1,"stat.damageDealt":1110,"stat.crouchOneCm":12,"stat.timeSinceDeath":14682,"stat.killEntity.Cow":2,"stat.useItem.minecraft.dirt":1,"stat.sprintOneCm":30422,"stat.mobKills":9,"achievement.exploreAllBiomes":{"value":0,"progress":["DesertHills","River","Plains"]},"stat.useItem.minecraft.diamond_sword":12,"stat.diveOneCm":329}